jcgraph/__init__.py
jcgraph/__main__.py
jcgraph/cli/__init__.py
jcgraph/cli/diagnose_command.py
jcgraph/cli/diagnostic_commands.py
jcgraph/cli/main.py
jcgraph/cli/mcp_commands.py
jcgraph/retriever/__init__.py
jcgraph/scanner/__init__.py
jcgraph/scanner/branch_detector.py
jcgraph/scanner/call_analyzer.py
jcgraph/scanner/file_scanner.py
jcgraph/scanner/java_parser.py
jcgraph/scanner/loop_detector.py
jcgraph/scanner/relation_builder.py
jcgraph/scanner/type_resolver.py
jcgraph/server/__init__.py
jcgraph/server/api.py
jcgraph/server/mcp_server.py
jcgraph/server/sequence_builder.py
jcgraph/server/static/graph.html
jcgraph/server/static/index.html
jcgraph/server/static/test_seq.html
jcgraph/server/static/js/app.js
jcgraph/server/static/js/sequence-loader.js
jcgraph/server/static/js/sequence-renderer.js
jcgraph/server/static/js/lib/alpine.min.js
jcgraph/server/static/js/lib/echarts.min.js
jcgraph/storage/__init__.py
jcgraph/storage/sqlite.py
jcgraph/utils/__init__.py
jcgraph/utils/db_finder.py
jcgraph/utils/logger.py
jcgraph-0.2.7.dist-info/licenses/LICENSE
jcgraph-0.2.7.dist-info/METADATA
jcgraph-0.2.7.dist-info/WHEEL
jcgraph-0.2.7.dist-info/entry_points.txt
jcgraph-0.2.7.dist-info/top_level.txt
jcgraph-0.2.7.dist-info/RECORD
