Metadata-Version: 2.4
Name: jcgraph
Version: 0.2.7
Summary: Java代码知识图谱构建工具 - 基于语义分析的 Java 项目理解和查询工具，支持 MCP Server
Author-email: Your Name <your.email@example.com>
License: MIT
Project-URL: Homepage, https://github.com/xuelin25/jcgraph
Project-URL: Documentation, https://github.com/xuelin25/jcgraph/blob/main/docs/MCP_SERVER_GUIDE.md
Project-URL: Repository, https://github.com/xuelin25/jcgraph
Project-URL: Issues, https://github.com/xuelin25/jcgraph/issues
Keywords: java,code-analysis,knowledge-graph,mcp-server,ai-tools,static-analysis
Classifier: Development Status :: 4 - Beta
Classifier: Intended Audience :: Developers
Classifier: Topic :: Software Development :: Code Generators
Classifier: Topic :: Software Development :: Libraries :: Python Modules
Classifier: License :: OSI Approved :: MIT License
Classifier: Programming Language :: Python :: 3
Classifier: Programming Language :: Python :: 3.9
Classifier: Programming Language :: Python :: 3.10
Classifier: Programming Language :: Python :: 3.11
Classifier: Programming Language :: Python :: 3.12
Requires-Python: >=3.9
License-File: LICENSE
Requires-Dist: click>=8.0
Requires-Dist: rich>=13.0
Requires-Dist: pyyaml>=6.0
Provides-Extra: full
Requires-Dist: tree-sitter>=0.21; extra == "full"
Requires-Dist: tree-sitter-java>=0.21; extra == "full"
Requires-Dist: fastapi>=0.100; extra == "full"
Requires-Dist: uvicorn>=0.20; extra == "full"
Requires-Dist: chromadb>=0.4; extra == "full"
Requires-Dist: networkx>=3.0; extra == "full"
Provides-Extra: mcp
Requires-Dist: mcp>=0.9.0; python_version >= "3.10" and extra == "mcp"
Provides-Extra: dev
Requires-Dist: pytest>=7.0; extra == "dev"
Requires-Dist: black>=23.0; extra == "dev"
Requires-Dist: ruff>=0.1; extra == "dev"
Dynamic: license-file
